owasp_nest_sdk/__init__.py
owasp_nest_sdk/sdk.py
owasp_nest_sdk/sdk_async.py
owasp_nest_sdk/hooks/__init__.py
owasp_nest_sdk/hooks/hook.py
owasp_nest_sdk/models/__init__.py
owasp_nest_sdk/models/chapter_schema.py
owasp_nest_sdk/models/committee_schema.py
owasp_nest_sdk/models/event_schema.py
owasp_nest_sdk/models/issue_schema.py
owasp_nest_sdk/models/label_schema.py
owasp_nest_sdk/models/list_chapters_ordering.py
owasp_nest_sdk/models/list_committees_ordering.py
owasp_nest_sdk/models/list_events_ordering.py
owasp_nest_sdk/models/list_issues_ordering.py
owasp_nest_sdk/models/list_labels_ordering.py
owasp_nest_sdk/models/list_organizations_ordering.py
owasp_nest_sdk/models/list_projects_ordering.py
owasp_nest_sdk/models/list_releases_ordering.py
owasp_nest_sdk/models/list_repositories_ordering.py
owasp_nest_sdk/models/list_users_ordering.py
owasp_nest_sdk/models/organization_schema.py
owasp_nest_sdk/models/paged_chapter_schema.py
owasp_nest_sdk/models/paged_committee_schema.py
owasp_nest_sdk/models/paged_event_schema.py
owasp_nest_sdk/models/paged_issue_schema.py
owasp_nest_sdk/models/paged_label_schema.py
owasp_nest_sdk/models/paged_organization_schema.py
owasp_nest_sdk/models/paged_project_schema.py
owasp_nest_sdk/models/paged_release_schema.py
owasp_nest_sdk/models/paged_repository_schema.py
owasp_nest_sdk/models/paged_user_schema.py
owasp_nest_sdk/models/project_level.py
owasp_nest_sdk/models/project_schema.py
owasp_nest_sdk/models/release_schema.py
owasp_nest_sdk/models/repository_schema.py
owasp_nest_sdk/models/state.py
owasp_nest_sdk/models/user_schema.py
owasp_nest_sdk/models/utils/__init__.py
owasp_nest_sdk/models/utils/base_model.py
owasp_nest_sdk/models/utils/cast_models.py
owasp_nest_sdk/models/utils/json_map.py
owasp_nest_sdk/models/utils/one_of_base_model.py
owasp_nest_sdk/models/utils/sentinel.py
owasp_nest_sdk/net/__init__.py
owasp_nest_sdk/net/environment/__init__.py
owasp_nest_sdk/net/environment/environment.py
owasp_nest_sdk/net/headers/__init__.py
owasp_nest_sdk-1.0.0.dist-info/METADATA
owasp_nest_sdk-1.0.0.dist-info/WHEEL
owasp_nest_sdk-1.0.0.dist-info/top_level.txt
owasp_nest_sdk-1.0.0.dist-info/RECORD
