Metadata-Version: 2.4
Name: owasp_nest_sdk
Version: 1.0.0
Summary: API for OWASP related entities
Requires-Python: >=3.9
Requires-Dist: requests>=2.31.0
